examples/code_diff.py
examples/load_diffs_from_json.py
examples/load_submodules.py
examples/parse_commit_diff.py
examples/parse_github_url.py
github_lib-0.9.0.dist-info/licenses/LICENSE
gitlib/__init__.py
gitlib/loader.py
gitlib/common/__init__.py
gitlib/common/constants.py
gitlib/common/enums.py
gitlib/common/exceptions.py
gitlib/github/__init__.py
gitlib/github/client.py
gitlib/github/commit.py
gitlib/github/file.py
gitlib/github/repository.py
gitlib/models/__init__.py
gitlib/models/submodule.py
gitlib/models/diff/__init__.py
gitlib/models/diff/file.py
gitlib/models/diff/hunk.py
gitlib/models/diff/line.py
gitlib/models/diff/patch.py
gitlib/models/url/__init__.py
gitlib/models/url/base.py
gitlib/models/url/commit.py
gitlib/models/url/issue.py
gitlib/models/url/pull_request.py
gitlib/models/url/repository.py
gitlib/parsers/__init__.py
gitlib/parsers/diff/__init__.py
gitlib/parsers/diff/base.py
gitlib/parsers/diff/git.py
gitlib/parsers/diff/helpers.py
gitlib/parsers/diff/unified.py
gitlib/parsers/patch/__init__.py
gitlib/parsers/patch/base.py
gitlib/parsers/patch/git.py
gitlib/parsers/patch/helpers.py
gitlib/parsers/patch/indented.py
gitlib/parsers/patch/unified.py
gitlib/parsers/url/__init__.py
gitlib/parsers/url/base.py
gitlib/parsers/url/utils.py
github_lib-0.9.0.dist-info/METADATA
github_lib-0.9.0.dist-info/WHEEL
github_lib-0.9.0.dist-info/top_level.txt
github_lib-0.9.0.dist-info/RECORD
