Metadata-Version: 2.4
Name: github_lib
Version: 0.9.0
Summary: A Python package that extends the GitHub API for parsing links, processing diff code changes, and more.
Author-email: Eduard Pinconschi <eduard.pinconschi@tecnico.ulisboa.pt>
License: MIT License
Project-URL: repository, https://github.com/epicosy/gitlib
Project-URL: homepage, https://github.com/epicosy/gitlib
Keywords: package,github,client
Classifier: Topic :: Software Development
Classifier: Programming Language :: Python
Classifier: Environment :: Console
Classifier: Intended Audience :: Developers
Requires-Python: >=3.10
License-File: LICENSE
Requires-Dist: pydantic>=2.10.5
Requires-Dist: tqdm>=4.67.1
Requires-Dist: requests>=2.32.3
Requires-Dist: pygithub>=2.5.0
Requires-Dist: pygit2>=1.17.0
Requires-Dist: jsbeautifier>=1.15.1
Provides-Extra: test
Requires-Dist: pytest; extra == "test"
Requires-Dist: pytest-cov; extra == "test"
Requires-Dist: coverage; extra == "test"
Requires-Dist: twine>=1.11.0; extra == "test"
Requires-Dist: setuptools>=38.6.0; extra == "test"
Requires-Dist: wheel>=0.31.0; extra == "test"
Dynamic: license-file
